<?xml version="1.0"?>
<Results version="1.0">
<ReportNode type="testrun">
<ReportNode type="Iteration">
<ReportNode type="Action">
<ReportNode type="Context">
<ReportNode type="Step">
<Data>
    <Name>"OpenText MF Connect"- Smart Identification</Name>
    <Description>&lt;P&gt;&lt;span class="text"&gt;The smart identification mechanism was invoked.&lt;/span&gt;&lt;/P&gt;&lt;P&gt;&lt;SPAN class=text&gt;Reason: object not unique (17 objects found)&lt;/SPAN&gt;&lt;/P&gt;           &lt;SPAN class=text&gt;&lt;b&gt;Original description:&lt;/b&gt;&lt;/SPAN&gt;&lt;br&gt;micclass=Browser&lt;br&gt;&lt;P&gt;&lt;FONT face=Verdana size=2&gt;&lt;SPAN class=text&gt;&lt;B&gt;Smart Identification Alternative Description: &lt;/B&gt;&lt;/SPAN&gt;&lt;/FONT&gt;&lt;/P&gt;&lt;FONT face=Verdana size=2&gt;&lt;u&gt;Base filter properties (17 objects found)&amp;nbsp;&lt;/FONT&gt;&lt;/u&gt;&lt;br&gt;
micclass=Browser&lt;br&gt;&lt;br&gt;&lt;FONT face=Verdana size=2&gt;&lt;u&gt;Optional filter properties&lt;/FONT&gt;&lt;/u&gt;&lt;br&gt;
name=OpenText MF Connect&lt;SPAN class=passed&gt; (Used&lt;/SPAN&gt;, 1 matches)&lt;/SPAN&gt;&lt;br&gt;title=OpenText MF Connect&lt;SPAN class=warning&gt; (Ignored)&lt;FONT color=#000000&gt;&lt;/FONT&gt;&lt;/SPAN&gt;&lt;br&gt;openurl=http://10.119.32.204:8081/ConnectWeb&lt;SPAN class=warning&gt; (Ignored)&lt;FONT color=#000000&gt;&lt;/FONT&gt;&lt;/SPAN&gt;&lt;br&gt;opentitle=OpenText MF Connect&lt;SPAN class=warning&gt; (Ignored)&lt;FONT color=#000000&gt;&lt;/FONT&gt;&lt;/SPAN&gt;&lt;br&gt;openedbytestingtool=0&lt;SPAN class=warning&gt; (Ignored)&lt;FONT color=#000000&gt;&lt;/FONT&gt;&lt;/SPAN&gt;&lt;br&gt;number of tabs=15&lt;SPAN class=warning&gt; (Ignored)&lt;FONT color=#000000&gt;&lt;/FONT&gt;&lt;/SPAN&gt;&lt;br&gt;</Description>
    <StartTime>2026-02-16 14:26:51</StartTime>
    <Result>Done</Result>
    <Extension>
      <SmartIdentificationInfo>
        <SIDBasicProperties>
          <Property>
            <Name><![CDATA[micclass]]></Name>
            <Value><![CDATA[Browser]]></Value>
          </Property>
          <BasicMatch>17</BasicMatch>
        </SIDBasicProperties>
        <SIDOptionalProperties>
          <Property>
            <Name><![CDATA[name]]></Name>
            <Value><![CDATA[OpenText MF Connect]]></Value>
            <Info><![CDATA[Used]]></Info>
            <Matches>1</Matches>
          </Property>
          <Property>
            <Name><![CDATA[title]]></Name>
            <Value><![CDATA[OpenText MF Connect]]></Value>
            <Info><![CDATA[Ignored]]></Info>
            <Matches>0</Matches>
          </Property>
          <Property>
            <Name><![CDATA[openurl]]></Name>
            <Value><![CDATA[http://10.119.32.204:8081/ConnectWeb]]></Value>
            <Info><![CDATA[Ignored]]></Info>
            <Matches>0</Matches>
          </Property>
          <Property>
            <Name><![CDATA[opentitle]]></Name>
            <Value><![CDATA[OpenText MF Connect]]></Value>
            <Info><![CDATA[Ignored]]></Info>
            <Matches>0</Matches>
          </Property>
          <Property>
            <Name><![CDATA[openedbytestingtool]]></Name>
            <Value><![CDATA[False]]></Value>
            <Info><![CDATA[Ignored]]></Info>
            <Matches>0</Matches>
          </Property>
          <Property>
            <Name><![CDATA[number of tabs]]></Name>
            <Value><![CDATA[15]]></Value>
            <Info><![CDATA[Ignored]]></Info>
            <Matches>0</Matches>
          </Property>
        </SIDOptionalProperties>
      </SmartIdentificationInfo>
      <TestObject>
        <Repository>Local</Repository>
        <Path>
          <Object>
            <Type>Browser</Type>
            <Name><![CDATA[OpenText MF Connect]]></Name>
          </Object>
        </Path>
        <OperationData><![CDATA[<P><span class="text">The smart identification mechanism was invoked.</span></P><P><SPAN class=text>Reason: object not unique (17 objects found)</SPAN></P>           <SPAN class=text><b>Original description:</b></SPAN><br>micclass=Browser<br><P><FONT face=Verdana size=2><SPAN class=text><B>Smart Identification Alternative Description: </B></SPAN></FONT></P><FONT face=Verdana size=2><u>Base filter properties (17 objects found)&nbsp;</FONT></u><br>
micclass=Browser<br><br><FONT face=Verdana size=2><u>Optional filter properties</FONT></u><br>
name=OpenText MF Connect<SPAN class=passed> (Used</SPAN>, 1 matches)</SPAN><br>title=OpenText MF Connect<SPAN class=warning> (Ignored)<FONT color=#000000></FONT></SPAN><br>openurl=http://10.119.32.204:8081/ConnectWeb<SPAN class=warning> (Ignored)<FONT color=#000000></FONT></SPAN><br>opentitle=OpenText MF Connect<SPAN class=warning> (Ignored)<FONT color=#000000></FONT></SPAN><br>openedbytestingtool=0<SPAN class=warning> (Ignored)<FONT color=#000000></FONT></SPAN><br>number of tabs=15<SPAN class=warning> (Ignored)<FONT color=#000000></FONT></SPAN><br>]]></OperationData>
      </TestObject>
      <IconKey>bd8f4ca9ff404569a786d56f045aee26</IconKey>
      <IsPlainTextNodeName>True</IsPlainTextNodeName>
    </Extension>
    <DeviceInfo />
  </Data>
</ReportNode>
<ReportNode type="Step">
<Data>
    <Name>OpenText MF Connect.Navigate</Name>
    <Description>Navigate to http://10.119.32.204:8081/ConnectWeb&lt;br&gt;Target Frame: _top&lt;br&gt;Post Data: &lt;br&gt;HTTP Headers: </Description>
    <StartTime>2026-02-16 14:26:51</StartTime>
    <Result>Done</Result>
    <Extension>
      <TestObject>
        <Repository>Local</Repository>
        <Path>
          <Object>
            <Type>Browser</Type>
            <Name><![CDATA[OpenText MF Connect]]></Name>
          </Object>
        </Path>
        <Operation>Navigate</Operation>
        <OperationData><![CDATA[Navigate to http://10.119.32.204:8081/ConnectWeb<br>Target Frame: _top<br>Post Data: <br>HTTP Headers: ]]></OperationData>
      </TestObject>
      <IconKey>2fcd8ad3d2b3412a97193c655627a354</IconKey>
      <IsPlainTextNodeName>True</IsPlainTextNodeName>
    </Extension>
    <DeviceInfo />
  </Data>
</ReportNode>
<ReportNode type="Context">
<ReportNode type="Step">
<Data>
    <Name>Username.Set</Name>
    <Description>"Opentext"</Description>
    <StartTime>2026-02-16 14:26:53</StartTime>
    <Result>Done</Result>
    <Extension>
      <TestObject>
        <Repository>Local</Repository>
        <Path>
          <Object>
            <Type>Browser</Type>
            <Name><![CDATA[OpenText MF Connect]]></Name>
          </Object>
          <Object>
            <Type>Page</Type>
            <Name><![CDATA[OpenText MF Connect]]></Name>
          </Object>
          <Object>
            <Type>WebEdit</Type>
            <Name><![CDATA[Username]]></Name>
          </Object>
        </Path>
        <Operation>Set</Operation>
        <OperationData><![CDATA["Opentext"]]></OperationData>
        <Properties>
          <Property>
            <Name><![CDATA[type]]></Name>
            <Value><![CDATA[text]]></Value>
          </Property>
          <Property>
            <Name><![CDATA[name]]></Name>
            <Value><![CDATA[username]]></Value>
          </Property>
          <Property>
            <Name><![CDATA[html tag]]></Name>
            <Value><![CDATA[INPUT]]></Value>
          </Property>
        </Properties>
      </TestObject>
      <IconKey>30be40d64e914ed4b709e00b1cbb7deb</IconKey>
      <IsPlainTextNodeName>True</IsPlainTextNodeName>
    </Extension>
    <DeviceInfo />
  </Data>
</ReportNode>
<ReportNode type="Step">
<Data>
    <Name>Password.SetSecure</Name>
    <Description>"69930c0602bc7ca82d765847a13b2cc58d8c0f5a5ab1"</Description>
    <StartTime>2026-02-16 14:26:53</StartTime>
    <Result>Done</Result>
    <Extension>
      <TestObject>
        <Repository>Local</Repository>
        <Path>
          <Object>
            <Type>Browser</Type>
            <Name><![CDATA[OpenText MF Connect]]></Name>
          </Object>
          <Object>
            <Type>Page</Type>
            <Name><![CDATA[OpenText MF Connect]]></Name>
          </Object>
          <Object>
            <Type>WebEdit</Type>
            <Name><![CDATA[Password]]></Name>
          </Object>
        </Path>
        <Operation>SetSecure</Operation>
        <OperationData><![CDATA["69930c0602bc7ca82d765847a13b2cc58d8c0f5a5ab1"]]></OperationData>
        <Properties>
          <Property>
            <Name><![CDATA[type]]></Name>
            <Value><![CDATA[password]]></Value>
          </Property>
          <Property>
            <Name><![CDATA[name]]></Name>
            <Value><![CDATA[password]]></Value>
          </Property>
          <Property>
            <Name><![CDATA[html tag]]></Name>
            <Value><![CDATA[INPUT]]></Value>
          </Property>
        </Properties>
      </TestObject>
      <IconKey>30be40d64e914ed4b709e00b1cbb7deb</IconKey>
      <IsPlainTextNodeName>True</IsPlainTextNodeName>
    </Extension>
    <DeviceInfo />
  </Data>
</ReportNode>
<ReportNode type="Step">
<Data>
    <Name>Sign In.Click</Name>
    <Description />
    <StartTime>2026-02-16 14:26:53</StartTime>
    <Result>Done</Result>
    <Extension>
      <TestObject>
        <Repository>Local</Repository>
        <Path>
          <Object>
            <Type>Browser</Type>
            <Name><![CDATA[OpenText MF Connect]]></Name>
          </Object>
          <Object>
            <Type>Page</Type>
            <Name><![CDATA[OpenText MF Connect]]></Name>
          </Object>
          <Object>
            <Type>WebButton</Type>
            <Name><![CDATA[Sign In]]></Name>
          </Object>
        </Path>
        <Operation>Click</Operation>
        <Properties>
          <Property>
            <Name><![CDATA[type]]></Name>
            <Value><![CDATA[]]></Value>
          </Property>
          <Property>
            <Name><![CDATA[name]]></Name>
            <Value><![CDATA[Sign In]]></Value>
          </Property>
          <Property>
            <Name><![CDATA[html tag]]></Name>
            <Value><![CDATA[A]]></Value>
          </Property>
        </Properties>
      </TestObject>
      <IconKey>4001690f53004d768ff9e997d6763a38</IconKey>
      <IsPlainTextNodeName>True</IsPlainTextNodeName>
    </Extension>
    <DeviceInfo />
  </Data>
</ReportNode>
<Data>
    <Name>OpenText MF Connect</Name>
    <Description>Page</Description>
    <StartTime>2026-02-16 14:26:53</StartTime>
    <Duration>17</Duration>
    <Result>Done</Result>
    <Extension>
      <TestObject>
        <Repository>Local</Repository>
        <Path>
          <Object>
            <Type>Browser</Type>
            <Name><![CDATA[OpenText MF Connect]]></Name>
          </Object>
          <Object>
            <Type>Page</Type>
            <Name><![CDATA[OpenText MF Connect]]></Name>
          </Object>
        </Path>
        <OperationData><![CDATA[Page]]></OperationData>
      </TestObject>
      <IconKey>3c288ec4371a40a9bed5971015f02938</IconKey>
      <IsPlainTextNodeName>True</IsPlainTextNodeName>
    </Extension>
  </Data>
</ReportNode>
<ReportNode type="Step">
<ReportNode type="Step">
<ReportNode type="Step">
<Data>
    <Name>Stop Run</Name>
    <Description>Run stopped by user.</Description>
    <StartTime>2026-02-16 14:27:13</StartTime>
    <Result>Information</Result>
    <Extension>
      <IconKey>7e09466be94f4064b0015f5292f43b9c</IconKey>
      <IsPlainTextNodeName>True</IsPlainTextNodeName>
    </Extension>
  </Data>
</ReportNode>
<Data>
    <Name>User Settings</Name>
    <Description>Cannot&amp;nbsp;identify&amp;nbsp;the&amp;nbsp;object&amp;nbsp;"User&amp;nbsp;Settings"&amp;nbsp;(of&amp;nbsp;class&amp;nbsp;WebButton).&lt;br/&gt;Verify&amp;nbsp;that&amp;nbsp;this&amp;nbsp;object's&amp;nbsp;properties&amp;nbsp;match&amp;nbsp;an&amp;nbsp;object&amp;nbsp;currently&amp;nbsp;displayed&amp;nbsp;in&amp;nbsp;your&amp;nbsp;application.&lt;br/&gt;&lt;br/&gt;Object's physical description:&lt;br&gt;role = button&lt;br&gt;Mercury Class = WebButton&lt;br&gt;Html Tag = A&lt;br&gt;_xpath = //A[@id="header-userSettings-icon"]&lt;br&gt;|Visible = -1&lt;br&gt;Value =  &lt;br&gt;Type = &lt;br&gt;Name =  &lt;br&gt;Html Id = header-userSettings-icon&lt;br&gt;DHTML Class = navButton bui-tb-icon-user x-unselectable x-box-item navButton-default-small navButton-after-title x-btn-over x-focus navButton-focus navButton-default-small-focus&lt;br&gt;acc_name = User Settings&lt;br&gt;</Description>
    <StartTime>2026-02-16 14:27:13</StartTime>
    <Duration>0</Duration>
    <Result>Warning</Result>
    <Extension>
      <TestObject>
        <Repository>Local</Repository>
        <Path>
          <Object>
            <Type>Browser</Type>
            <Name><![CDATA[OpenText MF Connect]]></Name>
          </Object>
          <Object>
            <Type>Page</Type>
            <Name><![CDATA[OpenText MF Connect]]></Name>
          </Object>
          <Object>
            <Type>WebButton</Type>
            <Name><![CDATA[User Settings]]></Name>
          </Object>
        </Path>
        <OperationData><![CDATA[Cannot&nbsp;identify&nbsp;the&nbsp;object&nbsp;"User&nbsp;Settings"&nbsp;(of&nbsp;class&nbsp;WebButton).<br/>Verify&nbsp;that&nbsp;this&nbsp;object's&nbsp;properties&nbsp;match&nbsp;an&nbsp;object&nbsp;currently&nbsp;displayed&nbsp;in&nbsp;your&nbsp;application.]]></OperationData>
        <Properties>
          <Property>
            <Name><![CDATA[type]]></Name>
            <Value><![CDATA[]]></Value>
          </Property>
          <Property>
            <Name><![CDATA[role]]></Name>
            <Value><![CDATA[button]]></Value>
          </Property>
          <Property>
            <Name><![CDATA[name]]></Name>
            <Value><![CDATA[ ]]></Value>
          </Property>
          <Property>
            <Name><![CDATA[html tag]]></Name>
            <Value><![CDATA[A]]></Value>
          </Property>
          <Property>
            <Name><![CDATA[acc_name]]></Name>
            <Value><![CDATA[User Settings]]></Value>
          </Property>
        </Properties>
      </TestObject>
      <IconKey>4001690f53004d768ff9e997d6763a38</IconKey>
      <IsPlainTextNodeName>True</IsPlainTextNodeName>
      <NodeType>Run Error</NodeType>
    </Extension>
    <DeviceInfo />
  </Data>
</ReportNode>
<Data>
    <Name>"OpenText MF Connect"- Smart Identification</Name>
    <Description>&lt;P&gt;&lt;span class="text"&gt;The smart identification mechanism was invoked.&lt;/span&gt;&lt;/P&gt;&lt;P&gt;&lt;SPAN class=text&gt;Reason: object not unique (16 objects found)&lt;/SPAN&gt;&lt;/P&gt;           &lt;SPAN class=text&gt;&lt;b&gt;Original description:&lt;/b&gt;&lt;/SPAN&gt;&lt;br&gt;micclass=Browser&lt;br&gt;&lt;P&gt;&lt;FONT face=Verdana size=2&gt;&lt;SPAN class=text&gt;&lt;B&gt;Smart Identification Alternative Description: &lt;/B&gt;&lt;/SPAN&gt;&lt;/FONT&gt;&lt;/P&gt;&lt;FONT face=Verdana size=2&gt;&lt;u&gt;Base filter properties (16 objects found)&amp;nbsp;&lt;/FONT&gt;&lt;/u&gt;&lt;br&gt;
micclass=Browser&lt;br&gt;&lt;br&gt;&lt;FONT face=Verdana size=2&gt;&lt;u&gt;Optional filter properties&lt;/FONT&gt;&lt;/u&gt;&lt;br&gt;
name=OpenText MF Connect&lt;SPAN class=Failed&gt; (Skipped)&lt;/SPAN&gt;&lt;br&gt;title=OpenText MF Connect&lt;SPAN class=Failed&gt; (Skipped)&lt;/SPAN&gt;&lt;br&gt;openurl=http://10.119.32.204:8081/ConnectWeb&lt;SPAN class=passed&gt; (Used&lt;/SPAN&gt;, 1 matches)&lt;/SPAN&gt;&lt;br&gt;opentitle=OpenText MF Connect&lt;SPAN class=warning&gt; (Ignored)&lt;FONT color=#000000&gt;&lt;/FONT&gt;&lt;/SPAN&gt;&lt;br&gt;openedbytestingtool=0&lt;SPAN class=warning&gt; (Ignored)&lt;FONT color=#000000&gt;&lt;/FONT&gt;&lt;/SPAN&gt;&lt;br&gt;number of tabs=15&lt;SPAN class=warning&gt; (Ignored)&lt;FONT color=#000000&gt;&lt;/FONT&gt;&lt;/SPAN&gt;&lt;br&gt;</Description>
    <StartTime>2026-02-16 14:27:10</StartTime>
    <Duration>3</Duration>
    <Result>Warning</Result>
    <Extension>
      <SmartIdentificationInfo>
        <SIDBasicProperties>
          <Property>
            <Name><![CDATA[micclass]]></Name>
            <Value><![CDATA[Browser]]></Value>
          </Property>
          <BasicMatch>16</BasicMatch>
        </SIDBasicProperties>
        <SIDOptionalProperties>
          <Property>
            <Name><![CDATA[name]]></Name>
            <Value><![CDATA[OpenText MF Connect]]></Value>
            <Info><![CDATA[Skipped]]></Info>
            <Matches>0</Matches>
          </Property>
          <Property>
            <Name><![CDATA[title]]></Name>
            <Value><![CDATA[OpenText MF Connect]]></Value>
            <Info><![CDATA[Skipped]]></Info>
            <Matches>0</Matches>
          </Property>
          <Property>
            <Name><![CDATA[openurl]]></Name>
            <Value><![CDATA[http://10.119.32.204:8081/ConnectWeb]]></Value>
            <Info><![CDATA[Used]]></Info>
            <Matches>1</Matches>
          </Property>
          <Property>
            <Name><![CDATA[opentitle]]></Name>
            <Value><![CDATA[OpenText MF Connect]]></Value>
            <Info><![CDATA[Ignored]]></Info>
            <Matches>0</Matches>
          </Property>
          <Property>
            <Name><![CDATA[openedbytestingtool]]></Name>
            <Value><![CDATA[False]]></Value>
            <Info><![CDATA[Ignored]]></Info>
            <Matches>0</Matches>
          </Property>
          <Property>
            <Name><![CDATA[number of tabs]]></Name>
            <Value><![CDATA[15]]></Value>
            <Info><![CDATA[Ignored]]></Info>
            <Matches>0</Matches>
          </Property>
        </SIDOptionalProperties>
      </SmartIdentificationInfo>
      <TestObject>
        <Repository>Local</Repository>
        <Path>
          <Object>
            <Type>Browser</Type>
            <Name><![CDATA[OpenText MF Connect]]></Name>
          </Object>
        </Path>
        <OperationData><![CDATA[<P><span class="text">The smart identification mechanism was invoked.</span></P><P><SPAN class=text>Reason: object not unique (16 objects found)</SPAN></P>           <SPAN class=text><b>Original description:</b></SPAN><br>micclass=Browser<br><P><FONT face=Verdana size=2><SPAN class=text><B>Smart Identification Alternative Description: </B></SPAN></FONT></P><FONT face=Verdana size=2><u>Base filter properties (16 objects found)&nbsp;</FONT></u><br>
micclass=Browser<br><br><FONT face=Verdana size=2><u>Optional filter properties</FONT></u><br>
name=OpenText MF Connect<SPAN class=Failed> (Skipped)</SPAN><br>title=OpenText MF Connect<SPAN class=Failed> (Skipped)</SPAN><br>openurl=http://10.119.32.204:8081/ConnectWeb<SPAN class=passed> (Used</SPAN>, 1 matches)</SPAN><br>opentitle=OpenText MF Connect<SPAN class=warning> (Ignored)<FONT color=#000000></FONT></SPAN><br>openedbytestingtool=0<SPAN class=warning> (Ignored)<FONT color=#000000></FONT></SPAN><br>number of tabs=15<SPAN class=warning> (Ignored)<FONT color=#000000></FONT></SPAN><br>]]></OperationData>
      </TestObject>
      <IconKey>bd8f4ca9ff404569a786d56f045aee26</IconKey>
      <IsPlainTextNodeName>True</IsPlainTextNodeName>
    </Extension>
    <DeviceInfo />
  </Data>
</ReportNode>
<Data>
    <Name>OpenText MF Connect</Name>
    <Description>&lt;table&gt;&lt;tr&gt;&lt;td&gt;&lt;span style="text-align : left; font-size : 12px; "&gt;Local Browser&lt;/span&gt;&lt;/td&gt;&lt;/tr&gt;&lt;/table&gt;</Description>
    <StartTime>2026-02-16 14:26:51</StartTime>
    <Duration>22</Duration>
    <Result>Warning</Result>
    <Extension>
      <TestObject>
        <Repository>Local</Repository>
        <Path>
          <Object>
            <Type>Browser</Type>
            <Name><![CDATA[OpenText MF Connect]]></Name>
          </Object>
        </Path>
        <OperationData><![CDATA[<table><tr><td><span style="text-align : left; font-size : 12px; ">Local Browser</span></td></tr></table>]]></OperationData>
      </TestObject>
      <IconKey>2fcd8ad3d2b3412a97193c655627a354</IconKey>
      <IsPlainTextNodeName>True</IsPlainTextNodeName>
    </Extension>
  </Data>
</ReportNode>
<Data>
    <Name>Chrome</Name>
    <Description />
    <StartTime>2026-02-16 14:26:40</StartTime>
    <Duration>33</Duration>
    <Result>Warning</Result>
    <InputParameters>
      <Parameter name="url" value="http://10.119.32.204:8081/ConnectWeb" type="System.String" />
    </InputParameters>
    <Extension>
      <IconKey>907b330b095743d6b1b9500eeae5476d</IconKey>
      <IsPlainTextNodeName>True</IsPlainTextNodeName>
    </Extension>
  </Data>
</ReportNode>
<Data>
    <Name>Action0</Name>
    <Description />
    <StartTime>2026-02-16 14:26:40</StartTime>
    <Duration>33</Duration>
    <Result>Warning</Result>
    <Extension>
      <IconKey>5c42c8f0a3d04d138160e4a62d3d4bcf</IconKey>
      <IsPlainTextNodeName>True</IsPlainTextNodeName>
    </Extension>
    <Index>1</Index>
    <TestedApplications />
  </Data>
</ReportNode>
<ReportNode type="Step">
<Data>
    <Name>Stop Run</Name>
    <Description>Run stopped by user.</Description>
    <StartTime>2026-02-16 14:27:13</StartTime>
    <Result>Information</Result>
    <Extension>
      <IconKey>5d1dfeb0b3ee47b2a915ce0bce8df9c3</IconKey>
      <IsPlainTextNodeName>True</IsPlainTextNodeName>
    </Extension>
  </Data>
</ReportNode>
<Data>
    <Name>MFConnectBrowsersTesChrome</Name>
    <ToolName>OpenText Functional Testing</ToolName>
    <ToolVersion>25.2</ToolVersion>
    <ToolVersionStringLiteral>25.2</ToolVersionStringLiteral>
    <Description />
    <StartTime>2026-02-16 14:26:36</StartTime>
    <Duration>37</Duration>
    <Result>Warning</Result>
    <InputParameters>
      <Parameter name="url" value="http://10.119.32.204:8081/ConnectWeb" type="System.String" />
    </InputParameters>
    <Extension>
      <IconKey>adeef8a7cc504eef9d3680838a5c1335</IconKey>
      <IsPlainTextNodeName>True</IsPlainTextNodeName>
    </Extension>
    <Environment>
      <Timezone>+02:00:00</Timezone>
      <Locale>English (Israel)</Locale>
      <User>OPENTEXT\rkarat</User>
      <CpuInfo>Intel(R) Core(TM) i7-10850H CPU @ 2.70GHz</CpuInfo>
      <NumberOfCores>12</NumberOfCores>
      <TotalMemory>65282</TotalMemory>
      <HostName>\OTX-8ZN56G3</HostName>
      <OSInfo>Windows 11 25H2 (x64)</OSInfo>
    </Environment>
    <TestedApplications />
    <Links>
      <Link type="DataTable" reference="Default.xlsx" displayname="Default Data Table" />
    </Links>
  </Data>
</ReportNode>
<GeneralInfo>
    <ResultName>Res2</ResultName>
    <RunStartTime>2026-02-16 14:26:36</RunStartTime>
    <Timezone>+02:00:00</Timezone>
    <OrchestrationToolName>OpenText Functional Testing</OrchestrationToolName>
    <OrchestrationToolVersion>25.2</OrchestrationToolVersion>
    <OrchestrationToolVersionStringLiteral>25.2</OrchestrationToolVersionStringLiteral>
  </GeneralInfo>
</Results>